{
  "family": "catalogue-app",
  "networkMode": "awsvpc",
  "requiresCompatibilities": ["FARGATE"],
  "cpu": "256",
  "memory": "512",
  "executionRoleArn": "${EXECUTION_ROLE_ARN}",
  "taskRoleArn": "${TASK_ROLE_ARN}",
  "containerDefinitions": [
    {
      "name": "app",
      "image": "PLACEHOLDER",
      "essential": true,
      "portMappings": [
        {
          "containerPort": 8000,
          "protocol": "tcp"
        }
      ],
      "healthCheck": {
        "command": ["CMD-SHELL", "curl -sf http://localhost:8000/health || exit 1"],
        "interval": 30,
        "timeout": 5,
        "retries": 3,
        "startPeriod": 10
      },
      "environment": [
        { "name": "LOG_LEVEL", "value": "INFO" },
        { "name": "UPLOAD_DIR", "value": "/app/uploads" },
        { "name": "STORAGE_BACKEND", "value": "s3" }
      ],
      "secrets": [
        {
          "name": "DATABASE_URL",
          "valueFrom": "arn:aws:secretsmanager:eu-west-2:ACCOUNT_ID:secret:catalogue/DATABASE_URL"
        },
        {
          "name": "API_KEY",
          "valueFrom": "arn:aws:secretsmanager:eu-west-2:ACCOUNT_ID:secret:catalogue/API_KEY"
        },
        {
          "name": "S3_BUCKET",
          "valueFrom": "arn:aws:secretsmanager:eu-west-2:ACCOUNT_ID:secret:catalogue/S3_BUCKET"
        }
      ],
      "logConfiguration": {
        "logDriver": "awslogs",
        "options": {
          "awslogs-group": "/ecs/catalogue-app",
          "awslogs-region": "eu-west-2",
          "awslogs-stream-prefix": "ecs"
        }
      }
    }
  ]
}
